docs/.gitignore
docs/Makefile
docs/conf.py
docs/index.md
docs/logo.py
docs/_static/logo-dark.svg
docs/_static/logo-long-dark.svg
docs/_static/logo-long.svg
docs/_static/logo.svg
docs/_templates/custom-class-template.rst
docs/_templates/custom-module-template.rst
docs/contributing/code_of_conduct.rst
docs/contributing/faq.rst
docs/contributing/index.rst
docs/contributing/scope.rst
docs/contributing/style.rst
docs/contributing/testing.rst
docs/examples/index.rst
docs/guide/backend.rst
docs/guide/cosmology.rst
docs/guide/experimental.rst
docs/guide/index.rst
docs/guide/installation.rst
docs/guide/likelihood.rst
docs/guide/models.rst
docs/guide/selection.rst
examples/GWTC1.ipynb
examples/GWTC3.ipynb
gwpopulation/__init__.py
gwpopulation/_version.py
gwpopulation/backend.py
gwpopulation/conversions.py
gwpopulation/hyperpe.py
gwpopulation/utils.py
gwpopulation/vt.py
gwpopulation/experimental/__init__.py
gwpopulation/experimental/cosmo_models.py
gwpopulation/experimental/jax.py
gwpopulation/experimental/numpyro.py
gwpopulation/models/__init__.py
gwpopulation/models/interped.py
gwpopulation/models/mass.py
gwpopulation/models/redshift.py
gwpopulation/models/spin.py
gwpopulation-1.3.1.dist-info/licenses/LICENSE.md
joss/paper.bib
joss/paper.md
gwpopulation-1.3.1.dist-info/METADATA
gwpopulation-1.3.1.dist-info/WHEEL
gwpopulation-1.3.1.dist-info/entry_points.txt
gwpopulation-1.3.1.dist-info/top_level.txt
gwpopulation-1.3.1.dist-info/RECORD
