Metadata-Version: 2.4
Name: gwpopulation
Version: 1.3.1
Summary: Unified population inference
Author-email: Colm Talbot <talbotcolm@gmail.com>
License: MIT License
Project-URL: Homepage, https://github.com/ColmTalbot/gwpopulation
Classifier: Programming Language :: Python :: 3.10
Classifier: Programming Language :: Python :: 3.11
Classifier: Programming Language :: Python :: 3.12
Classifier: Programming Language :: Python :: 3.13
Classifier: License :: OSI Approved :: MIT License
Classifier: Operating System :: OS Independent
Requires-Python: >=3.10
License-File: LICENSE.md
Requires-Dist: numpy>=1.16
Requires-Dist: scipy
Requires-Dist: pandas
Requires-Dist: tqdm
Requires-Dist: bilby>=2.7.0
Requires-Dist: cached_interpolate>=0.3.0
Requires-Dist: wcosmo>=0.3.0
Provides-Extra: pages
Requires-Dist: ipython_genutils; extra == "pages"
Requires-Dist: ipywidgets; extra == "pages"
Requires-Dist: jinja2; extra == "pages"
Requires-Dist: myst-parser; extra == "pages"
Requires-Dist: nbsphinx; extra == "pages"
Requires-Dist: numpydoc; extra == "pages"
Requires-Dist: pandoc; extra == "pages"
Requires-Dist: pydata-sphinx-theme; extra == "pages"
Requires-Dist: pygments; extra == "pages"
Requires-Dist: sphinx; extra == "pages"
Requires-Dist: sphinx_rtd_theme; extra == "pages"
Requires-Dist: sphinx-autoapi; extra == "pages"
Requires-Dist: sphinx-copybutton; extra == "pages"
Requires-Dist: sphinx-design; extra == "pages"
Requires-Dist: sphinx-tabs; extra == "pages"
Provides-Extra: test
Requires-Dist: pytest-cov; extra == "test"
Requires-Dist: pre-commit; extra == "test"
Requires-Dist: jupyter; extra == "test"
Requires-Dist: nbconvert; extra == "test"
Requires-Dist: astropy; extra == "test"
Requires-Dist: jax; extra == "test"
Requires-Dist: numpyro; extra == "test"
Requires-Dist: scipy; extra == "test"
Provides-Extra: cupy
Requires-Dist: cupy; extra == "cupy"
Provides-Extra: jax
Requires-Dist: jax; extra == "jax"
Requires-Dist: jaxlib; extra == "jax"
Dynamic: license-file
